<?xml version='1.0' encoding='UTF-8'?>
<song xmlns="http://openlyrics.info/namespace/2009/song" version="0.8" createdIn="OpenLP 2.4.6" modifiedIn="OpenLP 2.4.6" modifiedDate="2022-04-17T08:45:44">
  <properties>
    <titles>
      <title>Alleluja, magnificat</title>
    </titles>
    <authors>
      <author>Author Unknown</author>
    </authors>
  </properties>
  <lyrics>
    <verse name="v1">
      <lines>Alleluja, alleluja,<br/>Alleluja, alleluja,<br/>Alleluja, alleluja,<br/>Alleluja.</lines>
    </verse>
    <verse name="v2">
      <lines>Magasztald lelkem az Urat, és szívem ujjongjon én Megváltómban.</lines>
    </verse>
  </lyrics>
</song>
