<?xml version='1.0' encoding='UTF-8'?>
<song xmlns="http://openlyrics.info/namespace/2009/song" version="0.8" createdIn="OpenLP 2.4.6" modifiedIn="OpenLP 2.4.6" modifiedDate="2022-04-17T08:45:26">
  <properties>
    <titles>
      <title>Core of My Addiction</title>
    </titles>
    <authors>
      <author type="words">Fireflight</author>
      <author type="music">Fireflight</author>
    </authors>
    <songbooks>
      <songbook name="OpenSong: Zagraniczne"/>
    </songbooks>
  </properties>
  <lyrics>
    <verse name="v1">
      <lines>I'm aching, transparent.<br/>Your eyes see right through me.<br/>I'm dependent and shaking,<br/>I'm falling to my knees.</lines>
    </verse>
    <verse name="p1">
      <lines>And I can't contain this.<br/>You're the only one I need.<br/>I'm hooked and I cannot hide it.<br/>Your love's controlling me.</lines>
    </verse>
    <verse name="c1">
      <lines>You're the core of my addiction.<br/>I want to live, want to lose myself in You.<br/>You're the heart of my obsession.<br/>I want to live, but I would die for You.<br/>I'm addicted.</lines>
    </verse>
    <verse name="v2">
      <lines>Impulsive, enraptrued,<br/>This yearning's captured me.<br/>I'm determined, I'm not pretending.<br/>You are my destiny.</lines>
    </verse>
    <verse name="p2">
      <lines>I can feel the freedom.<br/>You're the only one I need.<br/>I'm alive and finally breathing.<br/>You're my recovery.</lines>
    </verse>
    <verse name="b1">
      <lines>God, I've waited for this day.<br/>I'll never run away.<br/>And You won't have to chase me.</lines>
    </verse>
    <verse name="b2">
      <lines>I'm addicted<br/>I'm addicted to You.</lines>
    </verse>
  </lyrics>
</song>
