<?xml version='1.0' encoding='UTF-8'?>
<song xmlns="http://openlyrics.info/namespace/2009/song" version="0.8" createdIn="OpenLP 2.4.6" modifiedIn="OpenLP 2.4.6" modifiedDate="2022-04-17T08:45:35">
  <properties>
    <titles>
      <title>Messiah is the King of kings</title>
    </titles>
    <authors>
      <author>Author Unknown</author>
    </authors>
    <songbooks>
      <songbook name="Rising Tabernakel"/>
    </songbooks>
  </properties>
  <lyrics>
    <verse name="v1">
      <lines>Messiah is the King of kings,<br/>Messiah is the Lord of lords.<br/>Messiah is the King of kings,<br/>Messiah is the Lord of lords.<br/>He is the King of kings,<br/>And the Lord of lords.<br/>Messiah is the King of kings,<br/>Messiah is the Lord of lords.</lines>
    </verse>
  </lyrics>
</song>
