<?xml version='1.0' encoding='UTF-8'?>
<song xmlns="http://openlyrics.info/namespace/2009/song" version="0.8" createdIn="OpenLP 2.4.6" modifiedIn="OpenLP 2.4.6" modifiedDate="2021-09-05T08:26:43">
  <properties>
    <titles>
      <title>pass me not o gentle saviour</title>
    </titles>
    <verseOrder>v1 c1 v2 c1 v3 c1 v4 c1</verseOrder>
    <authors>
      <author type="music">epic choir</author>
    </authors>
  </properties>
  <lyrics>
    <verse name="v1">
      <lines>pass me not , O gentle Saviour<br/>Hear my humble cry<br/>While on others thou art calling<br/>Do not pass me by </lines>
    </verse>
    <verse name="c1">
      <lines>Saviour! Saviour! <br/>Hear my humble cry <br/>While on other thou art calling<br/>Do not pass me by </lines>
    </verse>
    <verse name="v2">
      <lines>Let me at a throne of mercy <br/>Find a sweet relief <br/>Kneeling there in deep contrition<br/>Help my unbelief <br/></lines>
    </verse>
    <verse name="v3">
      <lines>Trusting only on thy merit<br/>Would i seek thy face<br/>Heal my wounded, broken spirit<br/>Save me by thy grace</lines>
    </verse>
    <verse name="v4">
      <lines>Thou the spring of all my comfort <br/>More than life to me <br/>Whom have i in earth beside thee <br/>Whom in heaven but thee ?</lines>
    </verse>
  </lyrics>
</song>
