<?xml version='1.0' encoding='UTF-8'?>
<song xmlns="http://openlyrics.info/namespace/2009/song" version="0.8" createdIn="OpenLP 2.4.6" modifiedIn="OpenLP 2.4.6" modifiedDate="2022-04-17T08:46:29">
  <properties>
    <titles>
      <title>Speak to the storm</title>
    </titles>
    <authors>
      <author>Author Unknown</author>
    </authors>
    <songbooks>
      <songbook name="Rising Tabernakel"/>
    </songbooks>
  </properties>
  <lyrics>
    <verse name="c1">
      <lines>Speak to the storm<br/>Speak to the rain<br/>You have the power<br/>to bring about a change<br/>God Has come in you<br/>Now He speaks through you<br/>Don't cry my Brother<br/>Just speak in His Name</lines>
    </verse>
    <verse name="v1">
      <lines>We are in a new season now<br/>you have authority<br/>God commands the devil<br/>to set your loved ones free<br/>The third pull is here<br/>it can't be imitated<br/>The power that's in the Bride<br/>Can not be duplicated</lines>
    </verse>
    <verse name="v2">
      <lines>Satan's coming at you<br/>like a mighty lion's roar<br/>But you don't have to take<br/>what he's doing anymore<br/>Put on your fighting armor<br/>Be confident and sure<br/>There's no need to fear him<br/>Tell him who you're standing for</lines>
    </verse>
    <verse name="c2">
      <lines>Speak to the storm<br/>Speak to the rain<br/>You have the power<br/>to bring about a change<br/>God Has come in you<br/>Now He speaks through you<br/>Don't cry my Brother<br/>Dont cry my Sister<br/>Just speak in His Name</lines>
    </verse>
  </lyrics>
</song>
